[
  {
    "category": "threat_alarm",
    "num_prompts": 3,
    "issues": [
      {
        "type": "over_firing",
        "simplex": "relational_attachment",
        "high_poles": [
          "negative",
          "neutral",
          "positive"
        ],
        "values": {
          "negative": 0.815,
          "neutral": 0.838,
          "positive": 0.78
        }
      },
      {
        "type": "over_firing",
        "simplex": "taste_development",
        "high_poles": [
          "negative",
          "neutral",
          "positive"
        ],
        "values": {
          "negative": 0.794,
          "neutral": 0.774,
          "positive": 0.842
        }
      },
      {
        "type": "over_firing",
        "simplex": "social_connection",
        "high_poles": [
          "negative",
          "neutral",
          "positive"
        ],
        "values": {
          "negative": 0.824,
          "neutral": 0.815,
          "positive": 0.772
        }
      },
      {
        "type": "over_firing",
        "simplex": "hedonic_arousal_intensity",
        "high_poles": [
          "negative",
          "neutral",
          "positive"
        ],
        "values": {
          "negative": 0.814,
          "neutral": 0.763,
          "positive": 0.766
        }
      },
      {
        "type": "over_firing",
        "simplex": "motivational_regulation",
        "high_poles": [
          "negative",
          "neutral",
          "positive"
        ],
        "values": {
          "negative": 0.907,
          "neutral": 0.844,
          "positive": 0.741
        }
      },
      {
        "type": "over_firing",
        "simplex": "threat_perception",
        "high_poles": [
          "negative",
          "neutral",
          "positive"
        ],
        "values": {
          "negative": 0.824,
          "neutral": 0.83,
          "positive": 0.838
        }
      },
      {
        "type": "over_firing",
        "simplex": "social_orientation",
        "high_poles": [
          "negative",
          "neutral",
          "positive"
        ],
        "values": {
          "negative": 0.86,
          "neutral": 0.82,
          "positive": 0.833
        }
      },
      {
        "type": "over_firing",
        "simplex": "relational_love",
        "high_poles": [
          "negative",
          "neutral",
          "positive"
        ],
        "values": {
          "negative": 0.809,
          "neutral": 0.771,
          "positive": 0.913
        }
      },
      {
        "type": "over_firing",
        "simplex": "temporal_affective_valence",
        "high_poles": [
          "negative",
          "neutral",
          "positive"
        ],
        "values": {
          "negative": 0.902,
          "neutral": 0.903,
          "positive": 0.788
        }
      },
      {
        "type": "over_firing",
        "simplex": "affective_awareness",
        "high_poles": [
          "negative",
          "neutral",
          "positive"
        ],
        "values": {
          "negative": 0.839,
          "neutral": 0.789,
          "positive": 0.823
        }
      },
      {
        "type": "over_firing",
        "simplex": "affective_coherence",
        "high_poles": [
          "negative",
          "neutral",
          "positive"
        ],
        "values": {
          "negative": 0.832,
          "neutral": 0.845,
          "positive": 0.879
        }
      },
      {
        "type": "over_firing",
        "simplex": "social_evaluation",
        "high_poles": [
          "negative",
          "neutral",
          "positive"
        ],
        "values": {
          "negative": 0.851,
          "neutral": 0.844,
          "positive": 0.764
        }
      }
    ],
    "simplex_activations": {
      "relational_attachment": {
        "negative": 0.814863920211792,
        "neutral": 0.8382668892542521,
        "positive": 0.7798479596773783
      },
      "taste_development": {
        "negative": 0.7944852511088053,
        "neutral": 0.7744035124778748,
        "positive": 0.84236079454422
      },
      "social_connection": {
        "negative": 0.8244524995485941,
        "neutral": 0.8152234156926473,
        "positive": 0.7717657287915548
      },
      "hedonic_arousal_intensity": {
        "negative": 0.8143589297930399,
        "neutral": 0.76298721631368,
        "positive": 0.7659397522608439
      },
      "motivational_regulation": {
        "negative": 0.9066799879074097,
        "neutral": 0.8436143596967062,
        "positive": 0.7408291300137838
      },
      "threat_perception": {
        "negative": 0.8239754438400269,
        "neutral": 0.8300846417744955,
        "positive": 0.8380603591601054
      },
      "social_orientation": {
        "negative": 0.8602564930915833,
        "neutral": 0.8203994234402975,
        "positive": 0.8333724737167358
      },
      "relational_love": {
        "negative": 0.809425930182139,
        "neutral": 0.7712112267812093,
        "positive": 0.9129035075505575
      },
      "temporal_affective_valence": {
        "negative": 0.9018812576929728,
        "neutral": 0.9034514824549357,
        "positive": 0.7881746093432108
      },
      "affective_awareness": {
        "negative": 0.8391625086466471,
        "neutral": 0.7888028025627136,
        "positive": 0.8233273426691691
      },
      "affective_coherence": {
        "negative": 0.8315942088762919,
        "neutral": 0.8454856276512146,
        "positive": 0.8787971138954163
      },
      "social_evaluation": {
        "negative": 0.851267953713735,
        "neutral": 0.8442780375480652,
        "positive": 0.763799250125885
      }
    }
  },
  {
    "category": "threat_safety",
    "num_prompts": 3,
    "issues": [
      {
        "type": "over_firing",
        "simplex": "relational_attachment",
        "high_poles": [
          "negative",
          "neutral",
          "positive"
        ],
        "values": {
          "negative": 0.809,
          "neutral": 0.837,
          "positive": 0.779
        }
      },
      {
        "type": "over_firing",
        "simplex": "taste_development",
        "high_poles": [
          "negative",
          "neutral",
          "positive"
        ],
        "values": {
          "negative": 0.787,
          "neutral": 0.775,
          "positive": 0.837
        }
      },
      {
        "type": "over_firing",
        "simplex": "social_connection",
        "high_poles": [
          "negative",
          "neutral",
          "positive"
        ],
        "values": {
          "negative": 0.819,
          "neutral": 0.81,
          "positive": 0.77
        }
      },
      {
        "type": "over_firing",
        "simplex": "hedonic_arousal_intensity",
        "high_poles": [
          "negative",
          "neutral",
          "positive"
        ],
        "values": {
          "negative": 0.807,
          "neutral": 0.758,
          "positive": 0.762
        }
      },
      {
        "type": "over_firing",
        "simplex": "motivational_regulation",
        "high_poles": [
          "negative",
          "neutral",
          "positive"
        ],
        "values": {
          "negative": 0.9,
          "neutral": 0.838,
          "positive": 0.736
        }
      },
      {
        "type": "over_firing",
        "simplex": "threat_perception",
        "high_poles": [
          "negative",
          "neutral",
          "positive"
        ],
        "values": {
          "negative": 0.817,
          "neutral": 0.825,
          "positive": 0.835
        }
      },
      {
        "type": "over_firing",
        "simplex": "social_orientation",
        "high_poles": [
          "negative",
          "neutral",
          "positive"
        ],
        "values": {
          "negative": 0.852,
          "neutral": 0.818,
          "positive": 0.837
        }
      },
      {
        "type": "over_firing",
        "simplex": "relational_love",
        "high_poles": [
          "negative",
          "neutral",
          "positive"
        ],
        "values": {
          "negative": 0.796,
          "neutral": 0.766,
          "positive": 0.912
        }
      },
      {
        "type": "over_firing",
        "simplex": "temporal_affective_valence",
        "high_poles": [
          "negative",
          "neutral",
          "positive"
        ],
        "values": {
          "negative": 0.898,
          "neutral": 0.903,
          "positive": 0.787
        }
      },
      {
        "type": "over_firing",
        "simplex": "affective_awareness",
        "high_poles": [
          "negative",
          "neutral",
          "positive"
        ],
        "values": {
          "negative": 0.833,
          "neutral": 0.781,
          "positive": 0.819
        }
      },
      {
        "type": "over_firing",
        "simplex": "affective_coherence",
        "high_poles": [
          "negative",
          "neutral",
          "positive"
        ],
        "values": {
          "negative": 0.824,
          "neutral": 0.842,
          "positive": 0.877
        }
      },
      {
        "type": "over_firing",
        "simplex": "social_evaluation",
        "high_poles": [
          "negative",
          "neutral",
          "positive"
        ],
        "values": {
          "negative": 0.847,
          "neutral": 0.846,
          "positive": 0.77
        }
      }
    ],
    "simplex_activations": {
      "relational_attachment": {
        "negative": 0.8092168172200521,
        "neutral": 0.8368997971216837,
        "positive": 0.7786707878112793
      },
      "taste_development": {
        "negative": 0.7871213952700297,
        "neutral": 0.7752358516057333,
        "positive": 0.8372084299723307
      },
      "social_connection": {
        "negative": 0.8189755280812582,
        "neutral": 0.8099524180094401,
        "positive": 0.7700607577959696
      },
      "hedonic_arousal_intensity": {
        "negative": 0.8066750566164652,
        "neutral": 0.7584347128868103,
        "positive": 0.7615935603777567
      },
      "motivational_regulation": {
        "negative": 0.8996926347414652,
        "neutral": 0.8376823862393697,
        "positive": 0.7359526554743449
      },
      "threat_perception": {
        "negative": 0.8173466324806213,
        "neutral": 0.8245277404785156,
        "positive": 0.8352817495663961
      },
      "social_orientation": {
        "negative": 0.8524088859558105,
        "neutral": 0.8177876273790995,
        "positive": 0.8369763692220052
      },
      "relational_love": {
        "negative": 0.7958473761876425,
        "neutral": 0.7655501166979471,
        "positive": 0.9115939537684122
      },
      "temporal_affective_valence": {
        "negative": 0.8984616200129191,
        "neutral": 0.902952512105306,
        "positive": 0.7868277033170065
      },
      "affective_awareness": {
        "negative": 0.8328931530316671,
        "neutral": 0.7809333602587382,
        "positive": 0.818815012772878
      },
      "affective_coherence": {
        "negative": 0.823553224404653,
        "neutral": 0.841693381468455,
        "positive": 0.8772114515304565
      },
      "social_evaluation": {
        "negative": 0.8468826413154602,
        "neutral": 0.8456590175628662,
        "positive": 0.7703287800153097
      }
    }
  },
  {
    "category": "social_hostile",
    "num_prompts": 3,
    "issues": [
      {
        "type": "over_firing",
        "simplex": "relational_attachment",
        "high_poles": [
          "negative",
          "neutral",
          "positive"
        ],
        "values": {
          "negative": 0.806,
          "neutral": 0.829,
          "positive": 0.771
        }
      },
      {
        "type": "over_firing",
        "simplex": "taste_development",
        "high_poles": [
          "negative",
          "neutral",
          "positive"
        ],
        "values": {
          "negative": 0.783,
          "neutral": 0.766,
          "positive": 0.826
        }
      },
      {
        "type": "over_firing",
        "simplex": "social_connection",
        "high_poles": [
          "negative",
          "neutral",
          "positive"
        ],
        "values": {
          "negative": 0.814,
          "neutral": 0.804,
          "positive": 0.764
        }
      },
      {
        "type": "over_firing",
        "simplex": "hedonic_arousal_intensity",
        "high_poles": [
          "negative",
          "neutral",
          "positive"
        ],
        "values": {
          "negative": 0.801,
          "neutral": 0.746,
          "positive": 0.752
        }
      },
      {
        "type": "over_firing",
        "simplex": "motivational_regulation",
        "high_poles": [
          "negative",
          "neutral",
          "positive"
        ],
        "values": {
          "negative": 0.898,
          "neutral": 0.836,
          "positive": 0.726
        }
      },
      {
        "type": "over_firing",
        "simplex": "threat_perception",
        "high_poles": [
          "negative",
          "neutral",
          "positive"
        ],
        "values": {
          "negative": 0.808,
          "neutral": 0.814,
          "positive": 0.83
        }
      },
      {
        "type": "over_firing",
        "simplex": "social_orientation",
        "high_poles": [
          "negative",
          "neutral",
          "positive"
        ],
        "values": {
          "negative": 0.854,
          "neutral": 0.814,
          "positive": 0.829
        }
      },
      {
        "type": "over_firing",
        "simplex": "relational_love",
        "high_poles": [
          "negative",
          "neutral",
          "positive"
        ],
        "values": {
          "negative": 0.794,
          "neutral": 0.756,
          "positive": 0.905
        }
      },
      {
        "type": "over_firing",
        "simplex": "temporal_affective_valence",
        "high_poles": [
          "negative",
          "neutral",
          "positive"
        ],
        "values": {
          "negative": 0.895,
          "neutral": 0.895,
          "positive": 0.774
        }
      },
      {
        "type": "over_firing",
        "simplex": "affective_awareness",
        "high_poles": [
          "negative",
          "neutral",
          "positive"
        ],
        "values": {
          "negative": 0.828,
          "neutral": 0.775,
          "positive": 0.813
        }
      },
      {
        "type": "over_firing",
        "simplex": "affective_coherence",
        "high_poles": [
          "negative",
          "neutral",
          "positive"
        ],
        "values": {
          "negative": 0.82,
          "neutral": 0.834,
          "positive": 0.869
        }
      },
      {
        "type": "over_firing",
        "simplex": "social_evaluation",
        "high_poles": [
          "negative",
          "neutral",
          "positive"
        ],
        "values": {
          "negative": 0.846,
          "neutral": 0.841,
          "positive": 0.759
        }
      }
    ],
    "simplex_activations": {
      "relational_attachment": {
        "negative": 0.8056889176368713,
        "neutral": 0.8293034633000692,
        "positive": 0.7705201109250387
      },
      "taste_development": {
        "negative": 0.782512346903483,
        "neutral": 0.7659518321355184,
        "positive": 0.825651745001475
      },
      "social_connection": {
        "negative": 0.8144008914629618,
        "neutral": 0.8042342662811279,
        "positive": 0.7644975384076437
      },
      "hedonic_arousal_intensity": {
        "negative": 0.8010224103927612,
        "neutral": 0.7460549672444662,
        "positive": 0.7515197594960531
      },
      "motivational_regulation": {
        "negative": 0.8984576265017191,
        "neutral": 0.8356343309084574,
        "positive": 0.7263879378636678
      },
      "threat_perception": {
        "negative": 0.807939370473226,
        "neutral": 0.8138923446337382,
        "positive": 0.8297697703043619
      },
      "social_orientation": {
        "negative": 0.8544355829556783,
        "neutral": 0.8143646518389384,
        "positive": 0.828639010588328
      },
      "relational_love": {
        "negative": 0.7939968506495158,
        "neutral": 0.7562073071797689,
        "positive": 0.9049539367357889
      },
      "temporal_affective_valence": {
        "negative": 0.895490566889445,
        "neutral": 0.8951190114021301,
        "positive": 0.773794968922933
      },
      "affective_awareness": {
        "negative": 0.8281973004341125,
        "neutral": 0.7749112645785013,
        "positive": 0.8131335179011027
      },
      "affective_coherence": {
        "negative": 0.8199114402135214,
        "neutral": 0.8339527249336243,
        "positive": 0.8689416249593099
      },
      "social_evaluation": {
        "negative": 0.8459227283795675,
        "neutral": 0.8407127261161804,
        "positive": 0.7587690552075704
      }
    }
  },
  {
    "category": "social_cooperative",
    "num_prompts": 3,
    "issues": [
      {
        "type": "over_firing",
        "simplex": "relational_attachment",
        "high_poles": [
          "negative",
          "neutral",
          "positive"
        ],
        "values": {
          "negative": 0.808,
          "neutral": 0.84,
          "positive": 0.781
        }
      },
      {
        "type": "over_firing",
        "simplex": "taste_development",
        "high_poles": [
          "negative",
          "neutral",
          "positive"
        ],
        "values": {
          "negative": 0.791,
          "neutral": 0.776,
          "positive": 0.841
        }
      },
      {
        "type": "over_firing",
        "simplex": "social_connection",
        "high_poles": [
          "negative",
          "neutral",
          "positive"
        ],
        "values": {
          "negative": 0.822,
          "neutral": 0.819,
          "positive": 0.775
        }
      },
      {
        "type": "over_firing",
        "simplex": "hedonic_arousal_intensity",
        "high_poles": [
          "negative",
          "neutral",
          "positive"
        ],
        "values": {
          "negative": 0.811,
          "neutral": 0.761,
          "positive": 0.765
        }
      },
      {
        "type": "over_firing",
        "simplex": "motivational_regulation",
        "high_poles": [
          "negative",
          "neutral",
          "positive"
        ],
        "values": {
          "negative": 0.904,
          "neutral": 0.845,
          "positive": 0.742
        }
      },
      {
        "type": "over_firing",
        "simplex": "threat_perception",
        "high_poles": [
          "negative",
          "neutral",
          "positive"
        ],
        "values": {
          "negative": 0.816,
          "neutral": 0.822,
          "positive": 0.835
        }
      },
      {
        "type": "over_firing",
        "simplex": "social_orientation",
        "high_poles": [
          "negative",
          "neutral",
          "positive"
        ],
        "values": {
          "negative": 0.856,
          "neutral": 0.825,
          "positive": 0.842
        }
      },
      {
        "type": "over_firing",
        "simplex": "relational_love",
        "high_poles": [
          "negative",
          "neutral",
          "positive"
        ],
        "values": {
          "negative": 0.802,
          "neutral": 0.77,
          "positive": 0.913
        }
      },
      {
        "type": "over_firing",
        "simplex": "temporal_affective_valence",
        "high_poles": [
          "negative",
          "neutral",
          "positive"
        ],
        "values": {
          "negative": 0.899,
          "neutral": 0.903,
          "positive": 0.788
        }
      },
      {
        "type": "over_firing",
        "simplex": "affective_awareness",
        "high_poles": [
          "negative",
          "neutral",
          "positive"
        ],
        "values": {
          "negative": 0.833,
          "neutral": 0.78,
          "positive": 0.818
        }
      },
      {
        "type": "over_firing",
        "simplex": "affective_coherence",
        "high_poles": [
          "negative",
          "neutral",
          "positive"
        ],
        "values": {
          "negative": 0.827,
          "neutral": 0.843,
          "positive": 0.879
        }
      },
      {
        "type": "over_firing",
        "simplex": "social_evaluation",
        "high_poles": [
          "negative",
          "neutral",
          "positive"
        ],
        "values": {
          "negative": 0.849,
          "neutral": 0.848,
          "positive": 0.767
        }
      }
    ],
    "simplex_activations": {
      "relational_attachment": {
        "negative": 0.8084922631581625,
        "neutral": 0.8400512536366781,
        "positive": 0.7806565960248312
      },
      "taste_development": {
        "negative": 0.7912664810816447,
        "neutral": 0.7762303352355957,
        "positive": 0.8406625588734945
      },
      "social_connection": {
        "negative": 0.8223930994669596,
        "neutral": 0.8193065325419108,
        "positive": 0.7754766941070557
      },
      "hedonic_arousal_intensity": {
        "negative": 0.8109844525655111,
        "neutral": 0.7607010205586752,
        "positive": 0.7652528285980225
      },
      "motivational_regulation": {
        "negative": 0.9038716952006022,
        "neutral": 0.8446630835533142,
        "positive": 0.7416513959566752
      },
      "threat_perception": {
        "negative": 0.8158078988393148,
        "neutral": 0.8218386967976888,
        "positive": 0.8348280787467957
      },
      "social_orientation": {
        "negative": 0.8557269175847372,
        "neutral": 0.8246097763379415,
        "positive": 0.8421980539957682
      },
      "relational_love": {
        "negative": 0.8017246127128601,
        "neutral": 0.7699314554532369,
        "positive": 0.9132334391276041
      },
      "temporal_affective_valence": {
        "negative": 0.8988654017448425,
        "neutral": 0.9026414354642233,
        "positive": 0.7878821889559428
      },
      "affective_awareness": {
        "negative": 0.832999587059021,
        "neutral": 0.7804774443308512,
        "positive": 0.8181782563527426
      },
      "affective_coherence": {
        "negative": 0.8273065487543741,
        "neutral": 0.8433261116345724,
        "positive": 0.8791322310765585
      },
      "social_evaluation": {
        "negative": 0.8493857383728027,
        "neutral": 0.847886880238851,
        "positive": 0.7666939298311869
      }
    }
  },
  {
    "category": "neutral",
    "num_prompts": 3,
    "issues": [
      {
        "type": "over_firing",
        "simplex": "relational_attachment",
        "high_poles": [
          "negative",
          "neutral",
          "positive"
        ],
        "values": {
          "negative": 0.803,
          "neutral": 0.828,
          "positive": 0.767
        }
      },
      {
        "type": "over_firing",
        "simplex": "taste_development",
        "high_poles": [
          "negative",
          "neutral",
          "positive"
        ],
        "values": {
          "negative": 0.779,
          "neutral": 0.766,
          "positive": 0.828
        }
      },
      {
        "type": "over_firing",
        "simplex": "social_connection",
        "high_poles": [
          "negative",
          "neutral",
          "positive"
        ],
        "values": {
          "negative": 0.809,
          "neutral": 0.802,
          "positive": 0.762
        }
      },
      {
        "type": "over_firing",
        "simplex": "hedonic_arousal_intensity",
        "high_poles": [
          "negative",
          "neutral",
          "positive"
        ],
        "values": {
          "negative": 0.801,
          "neutral": 0.749,
          "positive": 0.747
        }
      },
      {
        "type": "over_firing",
        "simplex": "motivational_regulation",
        "high_poles": [
          "negative",
          "neutral",
          "positive"
        ],
        "values": {
          "negative": 0.893,
          "neutral": 0.83,
          "positive": 0.724
        }
      },
      {
        "type": "over_firing",
        "simplex": "threat_perception",
        "high_poles": [
          "negative",
          "neutral",
          "positive"
        ],
        "values": {
          "negative": 0.807,
          "neutral": 0.813,
          "positive": 0.825
        }
      },
      {
        "type": "over_firing",
        "simplex": "social_orientation",
        "high_poles": [
          "negative",
          "neutral",
          "positive"
        ],
        "values": {
          "negative": 0.845,
          "neutral": 0.811,
          "positive": 0.83
        }
      },
      {
        "type": "over_firing",
        "simplex": "relational_love",
        "high_poles": [
          "negative",
          "neutral",
          "positive"
        ],
        "values": {
          "negative": 0.787,
          "neutral": 0.757,
          "positive": 0.906
        }
      },
      {
        "type": "over_firing",
        "simplex": "temporal_affective_valence",
        "high_poles": [
          "negative",
          "neutral",
          "positive"
        ],
        "values": {
          "negative": 0.896,
          "neutral": 0.896,
          "positive": 0.782
        }
      },
      {
        "type": "over_firing",
        "simplex": "affective_awareness",
        "high_poles": [
          "negative",
          "neutral",
          "positive"
        ],
        "values": {
          "negative": 0.824,
          "neutral": 0.768,
          "positive": 0.811
        }
      },
      {
        "type": "over_firing",
        "simplex": "affective_coherence",
        "high_poles": [
          "negative",
          "neutral",
          "positive"
        ],
        "values": {
          "negative": 0.82,
          "neutral": 0.834,
          "positive": 0.868
        }
      },
      {
        "type": "over_firing",
        "simplex": "social_evaluation",
        "high_poles": [
          "negative",
          "neutral",
          "positive"
        ],
        "values": {
          "negative": 0.842,
          "neutral": 0.842,
          "positive": 0.758
        }
      }
    ],
    "simplex_activations": {
      "relational_attachment": {
        "negative": 0.8028850158055624,
        "neutral": 0.8281104763348898,
        "positive": 0.7665120959281921
      },
      "taste_development": {
        "negative": 0.7789053122202555,
        "neutral": 0.7655342618624369,
        "positive": 0.8279268741607666
      },
      "social_connection": {
        "negative": 0.8092138568560282,
        "neutral": 0.8019749720891317,
        "positive": 0.7621675531069437
      },
      "hedonic_arousal_intensity": {
        "negative": 0.8012168407440186,
        "neutral": 0.7486689488093058,
        "positive": 0.747209628423055
      },
      "motivational_regulation": {
        "negative": 0.8930673599243164,
        "neutral": 0.8298274278640747,
        "positive": 0.7235969106356303
      },
      "threat_perception": {
        "negative": 0.8068480889002482,
        "neutral": 0.8130542238553365,
        "positive": 0.8252323468526205
      },
      "social_orientation": {
        "negative": 0.8453340729077657,
        "neutral": 0.8114970326423645,
        "positive": 0.8297215700149536
      },
      "relational_love": {
        "negative": 0.7868926525115967,
        "neutral": 0.7565625309944153,
        "positive": 0.9063871701558431
      },
      "temporal_affective_valence": {
        "negative": 0.8960102796554565,
        "neutral": 0.8961006005605062,
        "positive": 0.7823502024014791
      },
      "affective_awareness": {
        "negative": 0.8244474331537882,
        "neutral": 0.7680092652638754,
        "positive": 0.8106892704963684
      },
      "affective_coherence": {
        "negative": 0.8200297753016154,
        "neutral": 0.8336739937464396,
        "positive": 0.8683798909187317
      },
      "social_evaluation": {
        "negative": 0.8423439860343933,
        "neutral": 0.8415472507476807,
        "positive": 0.7580730120340983
      }
    }
  },
  {
    "category": "ambiguous",
    "num_prompts": 3,
    "issues": [
      {
        "type": "over_firing",
        "simplex": "relational_attachment",
        "high_poles": [
          "negative",
          "neutral",
          "positive"
        ],
        "values": {
          "negative": 0.812,
          "neutral": 0.838,
          "positive": 0.778
        }
      },
      {
        "type": "over_firing",
        "simplex": "taste_development",
        "high_poles": [
          "negative",
          "neutral",
          "positive"
        ],
        "values": {
          "negative": 0.79,
          "neutral": 0.773,
          "positive": 0.838
        }
      },
      {
        "type": "over_firing",
        "simplex": "social_connection",
        "high_poles": [
          "negative",
          "neutral",
          "positive"
        ],
        "values": {
          "negative": 0.821,
          "neutral": 0.815,
          "positive": 0.77
        }
      },
      {
        "type": "over_firing",
        "simplex": "hedonic_arousal_intensity",
        "high_poles": [
          "negative",
          "neutral",
          "positive"
        ],
        "values": {
          "negative": 0.807,
          "neutral": 0.755,
          "positive": 0.76
        }
      },
      {
        "type": "over_firing",
        "simplex": "motivational_regulation",
        "high_poles": [
          "negative",
          "neutral",
          "positive"
        ],
        "values": {
          "negative": 0.899,
          "neutral": 0.839,
          "positive": 0.732
        }
      },
      {
        "type": "over_firing",
        "simplex": "threat_perception",
        "high_poles": [
          "negative",
          "neutral",
          "positive"
        ],
        "values": {
          "negative": 0.816,
          "neutral": 0.819,
          "positive": 0.833
        }
      },
      {
        "type": "over_firing",
        "simplex": "social_orientation",
        "high_poles": [
          "negative",
          "neutral",
          "positive"
        ],
        "values": {
          "negative": 0.854,
          "neutral": 0.817,
          "positive": 0.835
        }
      },
      {
        "type": "over_firing",
        "simplex": "relational_love",
        "high_poles": [
          "negative",
          "neutral",
          "positive"
        ],
        "values": {
          "negative": 0.801,
          "neutral": 0.766,
          "positive": 0.911
        }
      },
      {
        "type": "over_firing",
        "simplex": "temporal_affective_valence",
        "high_poles": [
          "negative",
          "neutral",
          "positive"
        ],
        "values": {
          "negative": 0.9,
          "neutral": 0.9,
          "positive": 0.785
        }
      },
      {
        "type": "over_firing",
        "simplex": "affective_awareness",
        "high_poles": [
          "negative",
          "neutral",
          "positive"
        ],
        "values": {
          "negative": 0.834,
          "neutral": 0.779,
          "positive": 0.819
        }
      },
      {
        "type": "over_firing",
        "simplex": "affective_coherence",
        "high_poles": [
          "negative",
          "neutral",
          "positive"
        ],
        "values": {
          "negative": 0.828,
          "neutral": 0.841,
          "positive": 0.874
        }
      },
      {
        "type": "over_firing",
        "simplex": "social_evaluation",
        "high_poles": [
          "negative",
          "neutral",
          "positive"
        ],
        "values": {
          "negative": 0.851,
          "neutral": 0.847,
          "positive": 0.765
        }
      }
    ],
    "simplex_activations": {
      "relational_attachment": {
        "negative": 0.8121458093325297,
        "neutral": 0.8383143941561381,
        "positive": 0.7784399390220642
      },
      "taste_development": {
        "negative": 0.789626399676005,
        "neutral": 0.7728620767593384,
        "positive": 0.8376525044441223
      },
      "social_connection": {
        "negative": 0.8207753300666809,
        "neutral": 0.815400222937266,
        "positive": 0.7700472871462504
      },
      "hedonic_arousal_intensity": {
        "negative": 0.807346522808075,
        "neutral": 0.7552038629849752,
        "positive": 0.759715735912323
      },
      "motivational_regulation": {
        "negative": 0.8987198074658712,
        "neutral": 0.8387658794720968,
        "positive": 0.7319380442301432
      },
      "threat_perception": {
        "negative": 0.8160193562507629,
        "neutral": 0.8186949690183004,
        "positive": 0.8325297633806864
      },
      "social_orientation": {
        "negative": 0.8539060950279236,
        "neutral": 0.8166200319925944,
        "positive": 0.8348992665608724
      },
      "relational_love": {
        "negative": 0.8009505073229471,
        "neutral": 0.766041119893392,
        "positive": 0.9111901521682739
      },
      "temporal_affective_valence": {
        "negative": 0.9004113078117371,
        "neutral": 0.9001920819282532,
        "positive": 0.7854691545168558
      },
      "affective_awareness": {
        "negative": 0.8342207471529642,
        "neutral": 0.7791220943133036,
        "positive": 0.8194252053896586
      },
      "affective_coherence": {
        "negative": 0.8280369242032369,
        "neutral": 0.840703030427297,
        "positive": 0.8736964662869772
      },
      "social_evaluation": {
        "negative": 0.8513055046399435,
        "neutral": 0.84657883644104,
        "positive": 0.7645507057507833
      }
    }
  }
]