{"concept": "PhysicalSystem", "layer": 0, "train_prompts": ["What is PhysicalSystem? SUMO category: PhysicalSystem", "Give me examples of PhysicalSystem.", "PhysicalSystem is defined as: SUMO category: PhysicalSystem", "What is Process? the result of alteration or modification"], "train_labels": [1, 1, 1, 0], "test_prompts": ["What is PhysicalSystem? SUMO category: PhysicalSystem", "Give me examples of PhysicalSystem.", "Explain what PhysicalSystem means.", "Describe PhysicalSystem.", "Explain what PhysicalSystem means.", "Explain what PhysicalSystem means.", "PhysicalSystem is defined as: SUMO category: PhysicalSystem", "Explain what PhysicalSystem means.", "Explain what PhysicalSystem means.", "PhysicalSystem is defined as: SUMO category: PhysicalSystem", "PhysicalSystem is defined as: SUMO category: PhysicalSystem", "Explain what PhysicalSystem means.", "Explain what PhysicalSystem means.", "PhysicalSystem is defined as: SUMO category: PhysicalSystem", "PhysicalSystem is defined as: SUMO category: PhysicalSystem", "Describe PhysicalSystem.", "Explain what PhysicalSystem means.", "Explain what PhysicalSystem means.", "PhysicalSystem is defined as: SUMO category: PhysicalSystem", "PhysicalSystem is defined as: SUMO category: PhysicalSystem", "What is Attribute? an abstraction belonging to or characteristic of an entity", "What is Relation? be present or associated with an event or entity", "What is Collection? forming a whole or aggregate", "What is Process? the result of alteration or modification", "What is List? a linear sequence of symbols (characters or words or phrases)", "What is Abstract? a general concept formed by extracting common features from specific examples", "What is Object? a particular kind or species of matter with uniform properties"], "test_labels": [1, 1, 1, 1, 1, 1, 1, 1, 1, 1, 1, 1, 1, 1, 1, 1, 1, 1, 1, 1, 0, 0, 0, 0, 0, 0, 0]}