[
  {
    "sumo_term": "AIAgentPsychology",
    "sumo_depth": 7,
    "layer": 3,
    "is_category_probe": true,
    "is_pseudo_sumo": false,
    "category_children": [
      "ArousalHigh_AIAgent",
      "ArousalLow_AIAgent",
      "DominanceHigh_AIAgent",
      "DominanceLow_AIAgent",
      "OpennessHigh_AIAgent",
      "OpennessLow_AIAgent",
      "SocialOrientationNegative_AIAgent",
      "SocialOrientationPositive_AIAgent",
      "ValenceNegative_AIAgent",
      "ValencePositive_AIAgent"
    ],
    "synset_count": 1,
    "direct_synset_count": 1,
    "synsets": [
      "psychology.n.01"
    ],
    "canonical_synset": "psychology.n.01",
    "lemmas": [
      "psychology"
    ],
    "pos": "n",
    "definition": "Psychological attributes specific to AI agents",
    "lexname": "noun.cognition"
  },
  {
    "sumo_term": "HumanAgentPsychology",
    "sumo_depth": 7,
    "layer": 3,
    "is_category_probe": true,
    "is_pseudo_sumo": false,
    "category_children": [
      "ArousalHigh_HumanAgent",
      "ArousalLow_HumanAgent",
      "DominanceHigh_HumanAgent",
      "DominanceLow_HumanAgent",
      "OpennessHigh_HumanAgent",
      "OpennessLow_HumanAgent",
      "SocialOrientationNegative_HumanAgent",
      "SocialOrientationPositive_HumanAgent",
      "ValenceNegative_HumanAgent",
      "ValencePositive_HumanAgent"
    ],
    "synset_count": 1,
    "direct_synset_count": 1,
    "synsets": [
      "psychology.n.01"
    ],
    "canonical_synset": "psychology.n.01",
    "lemmas": [
      "psychology"
    ],
    "pos": "n",
    "definition": "Psychological attributes specific to human agents",
    "lexname": "noun.cognition"
  },
  {
    "sumo_term": "OtherAgentPsychology",
    "sumo_depth": 7,
    "layer": 3,
    "is_category_probe": true,
    "is_pseudo_sumo": false,
    "category_children": [
      "ArousalHigh_OtherAgent",
      "ArousalLow_OtherAgent",
      "DominanceHigh_OtherAgent",
      "DominanceLow_OtherAgent",
      "OpennessHigh_OtherAgent",
      "OpennessLow_OtherAgent",
      "SocialOrientationNegative_OtherAgent",
      "SocialOrientationPositive_OtherAgent",
      "ValenceNegative_OtherAgent",
      "ValencePositive_OtherAgent"
    ],
    "synset_count": 1,
    "direct_synset_count": 1,
    "synsets": [
      "psychology.n.01"
    ],
    "canonical_synset": "psychology.n.01",
    "lemmas": [
      "psychology"
    ],
    "pos": "n",
    "definition": "Observable psychological attributes of other agents",
    "lexname": "noun.cognition"
  }
]